pyqualys/__init__.py
pyqualys/errors/__init__.py
pyqualys/services/__init__.py
pyqualys/services/assetview/__init__.py
pyqualys/services/assetview/api_v2.py
pyqualys/services/assetview/host_assets.py
pyqualys/services/assetview/tag.py
pyqualys/services/common/__init__.py
pyqualys/services/report/__init__.py
pyqualys/services/report/html/__init__.py
pyqualys/services/report/html/html.py
pyqualys/services/report/html/template.py
pyqualys/services/report/plain/__init__.py
pyqualys/services/report/plain/plain.py
pyqualys/services/report/plain/template.py
pyqualys/services/vulnerability/__init__.py
pyqualys/services/vulnerability/api_v2.py
pyqualys/services/vulnerability/asset.py
pyqualys/services/vulnerability/asset_ips.py
pyqualys/services/vulnerability/report.py
pyqualys/services/vulnerability/scan.py
pyqualys/services/vulnerability/user.py
pyqualys/tests/__init__.py
pyqualys/tests/assetview_tests/__init__.py
pyqualys/tests/assetview_tests/test_host_asset.py
pyqualys/tests/assetview_tests/test_tag.py
pyqualys/tests/vulnerability_tests/__init__.py
pyqualys/tests/vulnerability_tests/test_assets.py
pyqualys/tests/vulnerability_tests/test_assets_ips.py
pyqualys/tests/vulnerability_tests/test_check_service_instance.py
pyqualys/tests/vulnerability_tests/test_get_services.py
pyqualys/tests/vulnerability_tests/test_report.py
pyqualys/tests/vulnerability_tests/test_user.py
pyqualys/utils/__init__.py
pyqualys/utils/connect.py
pyqualys/utils/session.py
pyqualys/utils/util.py
pyqualys-0.0.4.dist-info/METADATA
pyqualys-0.0.4.dist-info/WHEEL
pyqualys-0.0.4.dist-info/top_level.txt
pyqualys-0.0.4.dist-info/RECORD
