Metadata-Version: 2.1
Name: pyqualys
Version: 0.0.4
Summary: Qualys's python API client library.
Home-page: https://github.com/Amitgb14/pyqualys.git
Author: Amit Ghadge
Author-email: amitg.b14@gmail.com
License: UNKNOWN
Platform: UNKNOWN
Classifier: Programming Language :: Python :: 2.7
Classifier: Programming Language :: Python :: 3
Classifier: Programming Language :: Python :: 3.4
Classifier: Programming Language :: Python :: 3.5
Classifier: Programming Language :: Python :: 3.6
Requires-Dist: lxml (==4.1.1)
Requires-Dist: requests (>=2.18.1)
Requires-Dist: pep8 (==1.7.1)
Requires-Dist: simplejson (==3.15.0)
